gcgc/__init__.py
gcgc/alphabets.py
gcgc/vocab.py
gcgc/data/__init__.py
gcgc/tests/__init__.py
gcgc/tests/test_third_party.py
gcgc/tests/fixtures/__init__.py
gcgc/tests/tokenizer/__init__.py
gcgc/tests/tokenizer/test_kmer_tokenizer.py
gcgc/third_party/__init__.py
gcgc/third_party/hf_datasets.py
gcgc/third_party/hf_tokenizer.py
gcgc/tokenizer/__init__.py
gcgc/tokenizer/base.py
gcgc/tokenizer/kmer_tokenzier.py
gcgc-1.0.0.dist-info/LICENSE
gcgc-1.0.0.dist-info/METADATA
gcgc-1.0.0.dist-info/WHEEL
gcgc-1.0.0.dist-info/top_level.txt
gcgc-1.0.0.dist-info/RECORD
