Metadata-Version: 2.1
Name: gcgc
Version: 1.0.0
Summary: GCGC is a preprocessing library for biological sequence model development.
Home-page: http://gcgc.trenthauck.com/
Author: Trent Hauck
Author-email: trent@trenthauck.com
License: MIT
Project-URL: homepage, http://gcgc.trenthauck.com/
Project-URL: repository, https://github.com/tshauck/gcgc
Platform: UNKNOWN
Requires-Python: <4.0,>=3.6.1
Requires-Dist: pydantic (>=1.6.1)
Requires-Dist: importlib-metadata ; python_version < "3.8"
Provides-Extra: dev
Requires-Dist: pytest (~=5.0) ; extra == 'dev'
Requires-Dist: black (~=19.10b0) ; extra == 'dev'
Requires-Dist: mypy ; extra == 'dev'
Requires-Dist: mypy-extensions ; extra == 'dev'
Requires-Dist: pycodestyle (~=2.4) ; extra == 'dev'
Requires-Dist: pydocstyle (~=4.0) ; extra == 'dev'
Requires-Dist: pytest-cov (~=2.6) ; extra == 'dev'
Requires-Dist: mkdocs (==1.1.2) ; extra == 'dev'
Requires-Dist: mkdocs-material (==4.6.3) ; extra == 'dev'
Requires-Dist: phmdoctest ; extra == 'dev'
Requires-Dist: mkdocstrings ; extra == 'dev'
Requires-Dist: commitizen ; extra == 'dev'
Requires-Dist: pygments (~=2.3) ; extra == 'dev'
Requires-Dist: isort (~=4.3) ; extra == 'dev'
Requires-Dist: pylint (~=2.4) ; extra == 'dev'
Requires-Dist: twine (~=3.2) ; extra == 'dev'
Provides-Extra: hf
Requires-Dist: biopython (>=1.78) ; extra == 'hf'
Requires-Dist: tokenizers (==0.9.0) ; extra == 'hf'
Requires-Dist: datasets (==1.1.0) ; extra == 'hf'
Provides-Extra: include_package_data
Requires-Dist: True ; extra == 'include_package_data'
Provides-Extra: setup_requires
Requires-Dist: setuptools-scm (>=1.15) ; extra == 'setup_requires'
